corpuscula/__init__.py
corpuscula/_version.py
corpuscula/conllu.py
corpuscula/corpus_dict.py
corpuscula/corpus_utils.py
corpuscula/items.py
corpuscula/utils.py
corpuscula/wikipedia_utils.py
corpuscula-1.0.56.dist-info/LICENSE
corpuscula-1.0.56.dist-info/METADATA
corpuscula-1.0.56.dist-info/WHEEL
corpuscula-1.0.56.dist-info/top_level.txt
corpuscula-1.0.56.dist-info/RECORD
